ads_evt/__init__.py
ads_evt/spot.py
ads_evt-0.0.4.dist-info/METADATA
ads_evt-0.0.4.dist-info/WHEEL
ads_evt-0.0.4.dist-info/top_level.txt
ads_evt-0.0.4.dist-info/RECORD
