Metadata-Version: 2.1
Name: ads-evt
Version: 0.0.4
Summary: Anomaly Detection in Streams with Extreme Value Theory
Home-page: https://github.com/limjcst/ads-evt
Author: limjcst
License: GNU GPLv3
Project-URL: Bug Tracker, https://github.com/limjcst/ads-evt/issues
Classifier: Programming Language :: Python :: 3.6
Classifier: Operating System :: OS Independent
Requires-Python: >=3.6
Requires-Dist: matplotlib
Requires-Dist: numpy
Requires-Dist: pandas
Requires-Dist: scipy
